productmd/__init__.py
productmd/common.py
productmd/compose.py
productmd/composeinfo.py
productmd/discinfo.py
productmd/extra_files.py
productmd/images.py
productmd/modules.py
productmd/rpms.py
productmd/treeinfo.py
productmd-1.50.dist-info/licenses/AUTHORS
productmd-1.50.dist-info/licenses/LICENSE
productmd-1.50.dist-info/METADATA
productmd-1.50.dist-info/WHEEL
productmd-1.50.dist-info/top_level.txt
productmd-1.50.dist-info/RECORD
