Metadata-Version: 2.4
Name: productmd
Version: 1.50
Summary: Product, compose and installation media metadata library
Home-page: https://github.com/release-engineering/productmd
Author: Daniel Mach
Author-email: dmach@redhat.com
License: LGPLv2.1
License-File: LICENSE
License-File: AUTHORS
Dynamic: author
Dynamic: author-email
Dynamic: home-page
Dynamic: license
Dynamic: license-file
Dynamic: summary
